whisptray/__init__.py
whisptray/__main__.py
whisptray/alsa_error_handler.py
whisptray/alsa_redirect.cpython-39-aarch64-linux-gnu.so
whisptray/audio_capture.py
whisptray/essential_thread.py
whisptray/rate_limited_keyboard.py
whisptray/speech_to_keys.py
whisptray.libs/libasound-f8415949.so.2.0.0
whisptray-0.3.3.dist-info/METADATA
whisptray-0.3.3.dist-info/WHEEL
whisptray-0.3.3.dist-info/entry_points.txt
whisptray-0.3.3.dist-info/top_level.txt
whisptray-0.3.3.dist-info/RECORD
whisptray-0.3.3.dist-info/licenses/LICENSE
