Metadata-Version: 2.1
Name: whisptray
Version: 0.3.3
Summary: A simple dictation program using Whisper, pynput, and pystray. After installing, run with 'whisptray'. A tray icon will appear in the system tray. Click it to toggle dictation. Double click to exit.
Author-email: Brent Lewis <coder0xff@gmail.com>
License:                     GNU GENERAL PUBLIC LICENSE
Project-URL: Homepage, https://github.com/coder0xff/whisptray
Project-URL: Bug Tracker, https://github.com/coder0xff/whisptray/issues
Requires-Python: >=3.8
License-File: LICENSE
Requires-Dist: colorlog
Requires-Dist: numpy
Requires-Dist: openai-whisper
Requires-Dist: Pillow
Requires-Dist: sounddevice
Requires-Dist: pynput
Requires-Dist: pystray
Requires-Dist: torch
Provides-Extra: dev
Requires-Dist: black; extra == "dev"
Requires-Dist: build; extra == "dev"
Requires-Dist: flake8; extra == "dev"
Requires-Dist: isort; extra == "dev"
Requires-Dist: mypy; extra == "dev"
Requires-Dist: pylint; extra == "dev"
Requires-Dist: types-pynput; extra == "dev"
